ue4helpers/AWSUtils.py
ue4helpers/ArchiveUtils.py
ue4helpers/CacheUtils.py
ue4helpers/ConanUtils.py
ue4helpers/DescriptorData.py
ue4helpers/DockerUtils.py
ue4helpers/FilesystemUtils.py
ue4helpers/GCPUtils.py
ue4helpers/GitUtils.py
ue4helpers/PackagerBase.py
ue4helpers/PlatformInfo.py
ue4helpers/PluginPackager.py
ue4helpers/ProjectPackager.py
ue4helpers/SubprocessUtils.py
ue4helpers/UnrealUtils.py
ue4helpers/VersionHelpers.py
ue4helpers/__init__.py
ue4_ci_helpers-0.0.11.dist-info/LICENSE
ue4_ci_helpers-0.0.11.dist-info/METADATA
ue4_ci_helpers-0.0.11.dist-info/WHEEL
ue4_ci_helpers-0.0.11.dist-info/top_level.txt
ue4_ci_helpers-0.0.11.dist-info/zip-safe
ue4_ci_helpers-0.0.11.dist-info/RECORD
