Metadata-Version: 2.1
Name: ue4-ci-helpers
Version: 0.0.11
Summary: Unreal Engine 4 Continuous Integration helper functionality
Home-page: http://github.com/adamrehn/ue4-ci-helpers
Author: Adam Rehn
Author-email: adam@adamrehn.com
License: MIT
Keywords: epic unreal engine ci
Platform: UNKNOWN
Classifier: License :: OSI Approved :: MIT License
Classifier: Programming Language :: Python :: 3.5
Classifier: Programming Language :: Python :: 3.6
Classifier: Programming Language :: Python :: 3.7
Classifier: Topic :: Software Development :: Build Tools
Classifier: Environment :: Console
Requires-Python: >=3.5
Requires-Dist: boto3
Requires-Dist: conan (>=1.7.4)
Requires-Dist: conan-ue4cli (>=0.0.10)
Requires-Dist: docker (>=3.7.0)
Requires-Dist: google-auth (>=1.6.3)
Requires-Dist: google-cloud-storage (>=1.16.1)
Requires-Dist: requests
Requires-Dist: setuptools (>=38.6.0)
Requires-Dist: twine (>=1.11.0)
Requires-Dist: ue4cli (>=0.0.24)
Requires-Dist: wheel (>=0.31.0)
